{
  "version": 1,
  "site_id": "eisei2shu-master",
  "description": "二衛ガイドのゼロから作り直し用カタログ。keep は guide_seo_candidates の auto_decision=keep。",
  "promote_keep": [],
  "title_fixes": {
    "exam-format-overview": "第二種衛生管理者試験の形式【30問・五肢択一・約180分・300点満点】",
    "exam-scope-overview": "第二種衛生管理者試験の出題範囲の概要【3科目・30問の地図】",
    "subject-breakdown": "第二種衛生管理者試験の科目構成と配点【3科目×10問・各100点・180点・各40点】",
    "time-limit-strategy": "第二種衛生管理者試験の時間配分の戦略【30問・約6分/問】",
    "pass-score": "第二種衛生管理者試験の目標得点【総合180点・各科目40点ライン】",
    "goukaku-kijun": "第二種衛生管理者試験の合格基準と足切り【180点・各科目40点】",
    "pass-announcement-guide": "第二種衛生管理者試験の合格発表の確認方法【Web・郵送】",
    "exam-day-flow": "第二種衛生管理者試験の当日の流れ【13:30開始・30問・受付から提出まで】",
    "retake-strategy": "第二種衛生管理者試験の再受験の戦略【足切り科目の立て直し】",
    "past-questions-by-field": "第二種衛生管理者試験の分野別過去問の解き方【3科目×10問】",
    "3kagetsu-goukaku": "第二種衛生管理者試験の3ヶ月勉強計画【30問・週別ロードマップ】",
    "affiliate-mock-exam-materials": "第二種衛生管理者試験の模試・予想問題3選【30問本番形式2026】"
  },
  "section_headings": {
    "exam-format-overview": [
      "本試験の基本形式（30問・約180分）",
      "3科目と配点（各10問・各100点）",
      "合格基準（総合180点・各科目40点）",
      "マークシートの解答方法",
      "当サイト演習バンクとの違い",
      "次に読むページ"
    ],
    "goukaku-kijun": [
      "合格点の全体像（180点/300点）",
      "各科目の足切りライン（40点）",
      "演習での目標正答率の置き方",
      "足切りで落ちる典型パターン",
      "公式要項の確認手順",
      "関連ガイド"
    ],
    "3kagetsu-goukaku": [
      "3か月計画が向く人・向かない人",
      "残り週数から逆算した全体像",
      "週次の科目配分（3科目×10問）",
      "演習量と正答率の目安",
      "40点未満科目の底上げ",
      "直前2週の調整"
    ]
  },
  "write_priority": [
    "exam-format-overview",
    "goukaku-kijun",
    "pass-score",
    "subject-breakdown",
    "exam-scope-overview",
    "3kagetsu-goukaku",
    "past-questions-by-field",
    "textbook-selection",
    "field-law-basics",
    "field-rights-basics",
    "field-limit-basics",
    "time-limit-strategy",
    "exam-day-flow",
    "retake-strategy"
  ]
}
